
[
{"audio_type": "sound_effect", "layout": "background", "id":1, "action": "begin", "vol": -35, "desc": "Sound of rain falling"},
{"audio_type": "sound_effect", "layout": "background", "id":2, "action": "begin", "vol": -35, "desc": "Motor engine idling"},
{"audio_type": "speech", "layout": "foreground", "character": "man", "vol": -20, "text": "On a gloomy day, the city seems entranced by the rhythmic pattern of the falling rain."},
{"audio_type": "sound_effect", "layout": "background", "id":1, "action": "end"},
{"audio_type": "sound_effect", "layout": "background", "id":2, "action": "end"}
]
